kabir/__init__.py
kabir-0.0.1.dist-info/METADATA
kabir-0.0.1.dist-info/WHEEL
kabir-0.0.1.dist-info/RECORD
