Metadata-Version: 2.4
Name: kabir
Version: 0.0.1
Summary: The official package of Kabir.
Author-email: Kabir <kabir@aniate.com>
License: MIT
